aesthetics_predictor_api_pkg/__init__.py
aesthetics_predictor_api_pkg/config_files_creation.py
aesthetics_predictor_api_pkg/predictor_api_server.py
aesthetic_predictor_flask_api-1.0.2.dist-info/LICENSE
aesthetic_predictor_flask_api-1.0.2.dist-info/METADATA
aesthetic_predictor_flask_api-1.0.2.dist-info/WHEEL
aesthetic_predictor_flask_api-1.0.2.dist-info/top_level.txt
aesthetic_predictor_flask_api-1.0.2.dist-info/RECORD
